{
  "hash": "24ea8a98",
  "configHash": "f6403724",
  "lockfileHash": "f3e33bba",
  "browserHash": "ca78795d",
  "optimized": {
    "vue": {
      "src": "../../../node_modules/vue/dist/vue.runtime.esm-bundler.js",
      "file": "vue.js",
      "fileHash": "aa110319",
      "needsInterop": false
    },
    "vitepress > @vue/devtools-api": {
      "src": "../../../node_modules/@vue/devtools-api/dist/index.js",
      "file": "vitepress___@vue_devtools-api.js",
      "fileHash": "e63a9b2c",
      "needsInterop": false
    },
    "vitepress > @vueuse/core": {
      "src": "../../../node_modules/@vueuse/core/dist/index.js",
      "file": "vitepress___@vueuse_core.js",
      "fileHash": "3400df7b",
      "needsInterop": false
    },
    "vitepress > @vueuse/integrations/useFocusTrap": {
      "src": "../../../node_modules/@vueuse/integrations/dist/useFocusTrap.js",
      "file": "vitepress___@vueuse_integrations_useFocusTrap.js",
      "fileHash": "6bf2bcc1",
      "needsInterop": false
    },
    "vitepress > mark.js/src/vanilla.js": {
      "src": "../../../node_modules/mark.js/src/vanilla.js",
      "file": "vitepress___mark__js_src_vanilla__js.js",
      "fileHash": "d19f36e8",
      "needsInterop": false
    },
    "vitepress > minisearch": {
      "src": "../../../node_modules/minisearch/dist/es/index.js",
      "file": "vitepress___minisearch.js",
      "fileHash": "0c52ec6f",
      "needsInterop": false
    }
  },
  "chunks": {
    "chunk-ZVZS6IBK": {
      "file": "chunk-ZVZS6IBK.js"
    },
    "chunk-IJXOVSZR": {
      "file": "chunk-IJXOVSZR.js"
    }
  }
}